aquamarine/__init__.py
aquamarine/datasets/__init__.py
aquamarine/datasets/coco/__init__.py
aquamarine/datasets/coco/coco.py
aquamarine/datasets/coco/functional.py
aquamarine/datasets/utils/__init__.py
aquamarine/datasets/utils/visualize.py
aquamarine/datasets/vtouch/__init__.py
aquamarine/models/__init__.py
aquamarine/models/common/__init__.py
aquamarine/models/common/transformer/__init__.py
aquamarine/models/common/transformer/layers.py
aquamarine/models/detectors/__init__.py
aquamarine/models/detectors/detr/__init__.py
aquamarine/models/detectors/detr/detr.py
aquamarine/models/detectors/detr/layers.py
aquamarine/models/detectors/detr/matcher.py
aquamarine/models/detectors/detr/matchers.py
aquamarine/modules/__init__.py
aquamarine/modules/losses.py
aquamarine/modules/matchers.py
aquamarine-0.0.1.dist-info/METADATA
aquamarine-0.0.1.dist-info/WHEEL
aquamarine-0.0.1.dist-info/top_level.txt
aquamarine-0.0.1.dist-info/RECORD
