Metadata-Version: 2.1
Name: aquamarine
Version: 0.0.1
Summary: Object Detection Models - PyTorch
Home-page: https://github.com/ohjuno/Aquamarine
Author: jooh
Author-email: jooh@vtouch.io
License: UNKNOWN
Platform: UNKNOWN
Classifier: Programming Language :: Python :: 3
Classifier: Operating System :: OS Independent
Requires-Python: >=3.7
